odoo/addons/l10n_es_location_nuts/README.rst
odoo/addons/l10n_es_location_nuts/__init__.py
odoo/addons/l10n_es_location_nuts/__manifest__.py
odoo/addons/l10n_es_location_nuts/hooks.py
odoo/addons/l10n_es_location_nuts/i18n/ca.po
odoo/addons/l10n_es_location_nuts/i18n/es.po
odoo/addons/l10n_es_location_nuts/i18n/l10n_es_location_nuts.pot
odoo/addons/l10n_es_location_nuts/readme/CONFIGURE.md
odoo/addons/l10n_es_location_nuts/readme/CONTRIBUTORS.md
odoo/addons/l10n_es_location_nuts/readme/DESCRIPTION.md
odoo/addons/l10n_es_location_nuts/readme/USAGE.md
odoo/addons/l10n_es_location_nuts/static/description/icon.png
odoo/addons/l10n_es_location_nuts/static/description/index.html
odoo/addons/l10n_es_location_nuts/wizard/__init__.py
odoo/addons/l10n_es_location_nuts/wizard/nuts_import.py
odoo_addon_l10n_es_location_nuts-18.0.1.0.0.2.dist-info/METADATA
odoo_addon_l10n_es_location_nuts-18.0.1.0.0.2.dist-info/WHEEL
odoo_addon_l10n_es_location_nuts-18.0.1.0.0.2.dist-info/top_level.txt
odoo_addon_l10n_es_location_nuts-18.0.1.0.0.2.dist-info/RECORD
